hydraseq/__init__.py
hydraseq/automata.py
hydraseq/hydraseq.py
hydraseq-0.0.30.dist-info/LICENSE
hydraseq-0.0.30.dist-info/METADATA
hydraseq-0.0.30.dist-info/WHEEL
hydraseq-0.0.30.dist-info/top_level.txt
hydraseq-0.0.30.dist-info/RECORD
